cfgdir/__init__.py
cfgdir/cfgdir.py
cfgdir/version.py
cfgdir-1.0.11.data/data/LICENSE
cfgdir-1.0.11.data/data/VERSION
cfgdir-1.0.11.data/data/requirements.txt
cfgdir-1.0.11.dist-info/LICENSE
cfgdir-1.0.11.dist-info/METADATA
cfgdir-1.0.11.dist-info/WHEEL
cfgdir-1.0.11.dist-info/entry_points.txt
cfgdir-1.0.11.dist-info/top_level.txt
cfgdir-1.0.11.dist-info/RECORD
