Metadata-Version: 2.1
Name: cfgdir
Version: 1.0.11
Summary: output envdir as JSON or YAML
Home-page: https://github.com/rstms/cfgdir
Author: Matt Krueger
Author-email: mkrueger@rstms.net
License: MIT
Keywords: envdir configuration config
Platform: UNKNOWN
Classifier: Programming Language :: Python :: 2.7
Classifier: Programming Language :: Python :: 3
Classifier: License :: OSI Approved :: MIT License
Classifier: Operating System :: OS Independent
Classifier: Environment :: Console
License-File: LICENSE
Requires-Dist: click
Requires-Dist: pyyaml
